Metadata-Version: 2.1
Name: burl
Version: 2.0.1
Summary: a url shortening django app
Home-page: https://github.com/wryfi/burl
Author: Chris Haumesser
Author-email: chris.haumesser@gmail.com
License: UNKNOWN
Platform: UNKNOWN
Classifier: Environment :: Web Environment
Classifier: Framework :: Django :: 2.1
Classifier: License :: OSI Approved :: MIT License
Classifier: Natural Language :: English
Classifier: Topic :: Internet
Classifier: Topic :: Internet :: WWW/HTTP
Classifier: Programming Language :: Python :: 3.7
Classifier: Programming Language :: Python :: 3.8
Classifier: Programming Language :: Python :: 3.9
Classifier: Programming Language :: Python :: 3.10
Classifier: Operating System :: POSIX
Classifier: Operating System :: MacOS
Requires-Python: >=3.6
License-File: LICENSE
License-File: AUTHORS
